coronatracker/__init__.py
coronatracker-0.5.dist-info/LICENSE
coronatracker-0.5.dist-info/METADATA
coronatracker-0.5.dist-info/WHEEL
coronatracker-0.5.dist-info/top_level.txt
coronatracker-0.5.dist-info/RECORD
