Metadata-Version: 2.1
Name: coronatracker
Version: 0.5
Summary: A Python wrapper for Bing's COVID19 tracker.
Home-page: https://github.com/NCPlayz/coronatracker
Author: NCPlayz <Nadir Chowdhury>
Author-email: chowdhurynadir0@outlook.com
License: MIT
Platform: UNKNOWN
Classifier: Operating System :: OS Independent
Classifier: Programming Language :: Python :: 3
Classifier: Intended Audience :: Education
Classifier: License :: OSI Approved :: MIT License
Classifier: Topic :: Utilities
Classifier: Natural Language :: English
Classifier: Development Status :: 3 - Alpha
Classifier: Topic :: Software Development :: Libraries :: Python Modules
Requires-Python: >=3.7.0
Requires-Dist: selenium (>=3.4.0)
Requires-Dist: selenium-wire (==1.0.11)
